astar/__init__.py
astar/py.typed
astar-0.98.dist-info/LICENSE
astar-0.98.dist-info/METADATA
astar-0.98.dist-info/WHEEL
astar-0.98.dist-info/RECORD
