Metadata-Version: 2.1
Name: astar
Version: 0.98
Summary: generic A-Star path searching algorithm
Home-page: https://github.com/jrialland/python-astar
License: BSD
Author: J Rialland
Author-email: julien.rialland@gmail.com
Requires-Python: >=3.8,<4.0.0
Classifier: Intended Audience :: Developers
Classifier: License :: Other/Proprietary License
Classifier: Operating System :: OS Independent
Classifier: Programming Language :: Python
Classifier: Programming Language :: Python :: 3
Classifier: Programming Language :: Python :: 3.8
Classifier: Programming Language :: Python :: 3.9
Classifier: Programming Language :: Python :: 3.10
Classifier: Programming Language :: Python :: 3.11
Classifier: Topic :: Scientific/Engineering :: Information Analysis
Classifier: Topic :: Software Development :: Libraries :: Python Modules
Requires-Dist: sortedcontainers (>=2.4.0)
Project-URL: Repository, https://github.com/jrialland/python-astar
